lexset/LexsetManager.py
lexset/__init__.py
lexset/compression_artifacts.py
lexset/credentials.py
lexset/medtronic_Debug.py
lexset/review.py
lexset/test_ssim.py
lexset-4.2.9.dist-info/METADATA
lexset-4.2.9.dist-info/WHEEL
lexset-4.2.9.dist-info/top_level.txt
lexset-4.2.9.dist-info/RECORD
