Metadata-Version: 2.1
Name: lexset
Version: 4.2.9
Author: F. Bitonti
Author-email: Francis@lexset.ai
License: Apache 2.0
Classifier: Development Status :: 4 - Beta
Classifier: Programming Language :: Python :: 3
Requires-Dist: pyjson
Requires-Dist: PyYAML
Requires-Dist: pyBase64
Requires-Dist: tqdm
Requires-Dist: requests
Requires-Dist: matplotlib
Requires-Dist: numpy
Requires-Dist: opencv-python
Requires-Dist: scikit-image
Requires-Dist: scikit-learn
Requires-Dist: tensorflow
